mcp_server/__init__.py
mcp_server/server.py
mcp_server/schemas/__init__.py
mcp_server/schemas/mm1_schema.py
mcp_server_mm1/__init__.py
mcp_server_mm1/server.py
mcp_server_mm1/schemas/__init__.py
mcp_server_mm1/schemas/mm1_schema.py
mcp_server_mm1/simulations/__init__.py
mcp_server_mm1/simulations/mm1_queue.py
mcp_server_mm1/utils/__init__.py
mcp_server_mm1/utils/metrics.py
simulations/__init__.py
simulations/mm1_queue.py
utils/__init__.py
utils/metrics.py
mcp_server_mm1-0.1.5.dist-info/LICENSE.md
mcp_server_mm1-0.1.5.dist-info/METADATA
mcp_server_mm1-0.1.5.dist-info/WHEEL
mcp_server_mm1-0.1.5.dist-info/entry_points.txt
mcp_server_mm1-0.1.5.dist-info/top_level.txt
mcp_server_mm1-0.1.5.dist-info/RECORD
