Metadata-Version: 2.1
Name: mcp-server-mm1
Version: 0.1.5
Summary: Model Context Protocol server for M/M/1 queue simulation and analysis
Author-email: WSC 2025 Research Project <noreply@example.com>
License: MIT
Project-URL: Homepage, https://github.com/yourusername/mcp-server-mm1
Project-URL: Repository, https://github.com/yourusername/mcp-server-mm1
Project-URL: Issues, https://github.com/yourusername/mcp-server-mm1/issues
Project-URL: Documentation, https://github.com/yourusername/mcp-server-mm1#readme
Keywords: mcp,model-context-protocol,simulation,queue,mm1,queueing-theory,simpy,discrete-event-simulation
Classifier: Development Status :: 3 - Alpha
Classifier: Intended Audience :: Developers
Classifier: Intended Audience :: Science/Research
Classifier: License :: OSI Approved :: MIT License
Classifier: Programming Language :: Python :: 3
Classifier: Programming Language :: Python :: 3.10
Classifier: Programming Language :: Python :: 3.11
Classifier: Programming Language :: Python :: 3.12
Classifier: Topic :: Scientific/Engineering
Classifier: Topic :: Software Development :: Libraries :: Python Modules
Requires-Python: >=3.10
License-File: LICENSE.md
Requires-Dist: fastmcp>=1.0.0
Requires-Dist: mcp>=1.0.0
Requires-Dist: simpy>=4.0.0
Requires-Dist: numpy>=1.24.0
Requires-Dist: uvicorn>=0.27.0
Requires-Dist: starlette>=0.35.0
Provides-Extra: dev
Requires-Dist: pytest>=7.0.0; extra == "dev"
Requires-Dist: pytest-asyncio>=0.21.0; extra == "dev"
Requires-Dist: black>=23.0.0; extra == "dev"
Requires-Dist: ruff>=0.1.0; extra == "dev"
Requires-Dist: mypy>=1.0.0; extra == "dev"
